pyredis_manager/__init__.py
pyredis_manager/async_manager.py
pyredis_manager/manager.py
pyredis_manager/map.py
pyredis_manager-0.1.4.dist-info/licenses/LICENSE
tests/__init__.py
tests/async_test.py
tests/sync_test.py
pyredis_manager-0.1.4.dist-info/METADATA
pyredis_manager-0.1.4.dist-info/WHEEL
pyredis_manager-0.1.4.dist-info/top_level.txt
pyredis_manager-0.1.4.dist-info/RECORD
