Metadata-Version: 2.4
Name: pyredis_manager
Version: 0.1.4
Summary: A lightweight Redis client manager with sync/async support
Home-page: https://github.com/jackcizon/pyredis_manager
Author: jack-cizon
Author-email: jack-cizon <jack20021213cn@gmail.com>
License: MIT
Project-URL: Homepage, https://github.com/jackcizon/pyredis_manager
Keywords: redis,manager,flask,async,sync
Classifier: Programming Language :: Python :: 3
Classifier: License :: OSI Approved :: MIT License
Classifier: Operating System :: OS Independent
Requires-Python: >=3.6
License-File: LICENSE
Requires-Dist: redis>=4.3.6
Dynamic: author
Dynamic: home-page
Dynamic: license-file
Dynamic: requires-python
